CSST/CSST.py
csst_feh-0.0.8.dist-info/METADATA
csst_feh-0.0.8.dist-info/WHEEL
csst_feh-0.0.8.dist-info/licenses/LICENSE
csst_feh-0.0.8.dist-info/RECORD
